{
  "id": "7d6a32885497",
  "title": "AI deployment in financial services hits an inflexion point as Singapore leads the shift to production",
  "url": "https://www.artificialintelligence-news.com/news/financial-services-ai-deployment-singapore/",
  "source": "AI News",
  "published": "2026-02-13T08:00:00",
  "summary": "AI deployment in financial services has crossed a critical threshold, with only 2% of institutions globally reporting no AI use whatsoever—a dramatic indicator that the technology has moved...",
  "fetched_at": "2026-02-13T08:42:46.735595"
}